{"Directors": ["Mani Ratnam"], "Language": ["Tamil", "Hindi"], "Country": "India", "Runtime": 141, "Bio": "A Hindu man and a Muslim woman fall in love in a small village and move to Mumbai, where they have two children. However, growing religious tensions and erupting riots threaten to tear the family apart.", "genres": ["Drama", "Musical", "Romance"], "poster_url": "www.imdb.com/title/tt0112553/mediaviewer/rm4020112128", "name": "Bombay", "cast": [{"imdb_id": "nm0841552", "name": " Arvind Swam"}, {"imdb_id": "nm0463539", "name": " Manisha Koiral"}, {"imdb_id": "nm0621937", "name": " Nassa"}, {"imdb_id": "nm1390149", "name": " Kitt"}, {"imdb_id": "nm1218624", "name": " Master Harsh"}, {"imdb_id": "nm1389854", "name": " Master Hrida"}, {"imdb_id": "nm0695177", "name": " Prakash Ra"}, {"imdb_id": "nm0025627", "name": " Tinnu Anan"}, {"imdb_id": "nm0452021", "name": " Akash Khuran"}, {"imdb_id": "nm0007114", "name": " Sonali Bendr"}, {"imdb_id": "nm1377248", "name": " Nagendra Prasa"}, {"imdb_id": "nm1115041", "name": " M.V. Vasudeva Ra"}, {"imdb_id": "nm1391274", "name": " Ratnaka"}, {"imdb_id": "nm0707723", "name": " Rallapall"}, {"imdb_id": "nm1390550", "name": " Deesh Mariwal"}, {"imdb_id": "nm1390512", "name": " Vinay Malhotr"}, {"imdb_id": "nm1390666", "name": " Pramod Meno"}, {"imdb_id": "nm0038019", "name": " Aru"}, {"imdb_id": "nm1388212", "name": " A.R.S"}, {"imdb_id": "nm1388786", "name": " Vijaya Chandrik"}, {"imdb_id": "nm0705553", "name": " Radhaba"}, {"imdb_id": "nm0790659", "name": " Sheel"}, {"imdb_id": "nm1394724", "name": " Minu Ratho"}, {"imdb_id": "nm1394471", "name": " Padmini Nataraja"}, {"imdb_id": "nm1396015", "name": " Sreesh"}, {"imdb_id": "nm1391203", "name": " Priy"}, {"imdb_id": "nm2762787", "name": " Chetana Da"}]}