[{"imdb_id": "nm4731677", "name": " Ayushmann Khurran"}, {"imdb_id": "nm0007102", "name": " Tab"}, {"imdb_id": "nm2331000", "name": " Radhika Apt"}, {"imdb_id": "nm0223521", "name": " Anil Dhawa"}, {"imdb_id": "nm2435847", "name": " Manav Vi"}, {"imdb_id": "nm1817397", "name": " Ashwini Kalseka"}, {"imdb_id": "nm3777127", "name": " Chhaya Kada"}, {"imdb_id": "nm1664541", "name": " Zakir Hussai"}, {"imdb_id": "nm9139941", "name": " Rashmi Agdeka"}, {"imdb_id": "nm10134362", "name": " Abhishek Shukl"}, {"imdb_id": "nm10277342", "name": " Mohini Kewalraman"}, {"imdb_id": "nm10431412", "name": " Nikitasha Kapoo"}, {"imdb_id": "nm7927842", "name": " Saumin Pate"}, {"imdb_id": "nm10277369", "name": " Hera Saji"}, {"imdb_id": "nm10865771", "name": " Abhishek Anan"}, {"imdb_id": "nm10277354", "name": " Vishal Baja"}, {"imdb_id": "nm11534043", "name": " Yogesh Chandeka"}, {"imdb_id": "nm11351503", "name": " Abhishek Chaudhar"}, {"imdb_id": "nm11534044", "name": " Rahul Gajja"}, {"imdb_id": "nm11534048", "name": " Suchitra Mohit"}, {"imdb_id": "nm9271591", "name": " Pratik Nandkumar Mor"}, {"imdb_id": "nm11534046", "name": " Pankaj Poa"}, {"imdb_id": "nm6252382", "name": " Mahesh Ral"}, {"imdb_id": "nm9625502", "name": " Kabir Saji"}, {"imdb_id": "nm11534047", "name": " Swapnil Sawan"}, {"imdb_id": "nm11534042", "name": " Surabhi Sharm"}, {"imdb_id": "nm3385526", "name": " Gopal K. Sing"}, {"imdb_id": "nm11534045", "name": " Hemendra Pratap Sing"}, {"imdb_id": "nm7372243", "name": " Pawan Sing"}, {"imdb_id": "nm10948405", "name": " Akash Son"}, {"imdb_id": "nm1969626", "name": " Franco Va"}, {"imdb_id": "nm1589374", "name": " Jaydutt Vya"}]